{
  "type": "object",
  "properties": {
    "id": {
      "type": "string"
    },
    "name": {
      "type": "string"
    },
    "deleted": {
      "type": "boolean"
    },
    "website": {
      "type": ["string", "null"]
    },
    "emailAddress": {
      "type": ["string", "null"]
    },
    "phoneNumber": {
      "type": ["string", "null"]
    },
    "type": {
      "type": ["string", "null"]
    },
    "industry": {
      "type": ["string", "null"]
    },
    "sicCode": {
      "type": ["string", "null"]
    },
    "billingAddressStreet": {
      "type": ["string", "null"]
    },
    "billingAddressCity": {
      "type": ["string", "null"]
    },
    "billingAddressState": {
      "type": ["string", "null"]
    },
    "billingAddressCountry": {
      "type": ["string", "null"]
    },
    "billingAddressPostalCode": {
      "type": ["string", "null"]
    },
    "shippingAddressStreet": {
      "type": ["string", "null"]
    },
    "shippingAddressCity": {
      "type": ["string", "null"]
    },
    "shippingAddressState": {
      "type": ["string", "null"]
    },
    "shippingAddressCountry": {
      "type": ["string", "null"]
    },
    "shippingAddressPostalCode": {
      "type": ["string", "null"]
    },
    "description": {
      "type": ["string", "null"]
    },
    "createdAt": {
      "type": "string"
    },
    "modifiedAt": {
      "type": "string"
    },
    "electronicAddressScheme": {
      "type": ["string", "null"]
    },
    "electronicAddressIdentifier": {
      "type": ["string", "null"]
    },
    "emailAddressIsOptedOut": {
      "type": ["boolean", "null"]
    },
    "emailAddressIsInvalid": {
      "type": ["boolean", "null"]
    },
    "phoneNumberIsOptedOut": {
      "type": ["boolean", "null"]
    },
    "phoneNumberIsInvalid": {
      "type": ["boolean", "null"]
    },
    "emailAddressData": {
      "type": "array",
      "items": {}
    },
    "phoneNumberData": {
      "type": "array",
      "items": {}
    },
    "campaignId": {
      "type": ["string", "null"]
    },
    "campaignName": {
      "type": ["string", "null"]
    },
    "createdById": {
      "type": "string"
    },
    "createdByName": {
      "type": "string"
    },
    "modifiedById": {
      "type": ["string", "null"]
    },
    "modifiedByName": {
      "type": ["string", "null"]
    },
    "assignedUserId": {
      "type": ["string", "null"]
    },
    "assignedUserName": {
      "type": ["string", "null"]
    },
    "teamsIds": {
      "type": "array",
      "items": {}
    },
    "teamsNames": {
      "type": "object"
    },
    "originalLeadId": {
      "type": ["string", "null"]
    },
    "originalLeadName": {
      "type": ["string", "null"]
    },
    "priceBookId": {
      "type": ["string", "null"]
    },
    "priceBookName": {
      "type": ["string", "null"]
    },
    "isFollowed": {
      "type": "boolean"
    },
    "followersIds": {
      "type": "array",
      "items": {}
    },
    "followersNames": {
      "type": "object"
    },
    "isStarred": {
      "type": "boolean"
    },
    "supplierId": {
      "type": ["string", "null"]
    },
    "supplierName": {
      "type": ["string", "null"]
    }
  },
  "required": [
    "id",
    "name",
    "deleted",
    "website",
    "emailAddress",
    "phoneNumber",
    "type",
    "industry",
    "sicCode",
    "billingAddressStreet",
    "billingAddressCity",
    "billingAddressState",
    "billingAddressCountry",
    "billingAddressPostalCode",
    "shippingAddressStreet",
    "shippingAddressCity",
    "shippingAddressState",
    "shippingAddressCountry",
    "shippingAddressPostalCode",
    "description",
    "createdAt",
    "modifiedAt",
    "electronicAddressScheme",
    "electronicAddressIdentifier",
    "emailAddressIsOptedOut",
    "emailAddressIsInvalid",
    "phoneNumberIsOptedOut",
    "phoneNumberIsInvalid",
    "emailAddressData",
    "phoneNumberData",
    "campaignId",
    "campaignName",
    "createdById",
    "createdByName",
    "modifiedById",
    "modifiedByName",
    "assignedUserId",
    "assignedUserName",
    "teamsIds",
    "teamsNames",
    "originalLeadId",
    "originalLeadName",
    "priceBookId",
    "priceBookName",
    "isFollowed",
    "followersIds",
    "followersNames",
    "isStarred",
    "supplierId",
    "supplierName"
  ]
}
